occli/__init__.py
occli/banner.py
occli/main.py
occli-0.3.5.dist-info/LICENSE
occli-0.3.5.dist-info/METADATA
occli-0.3.5.dist-info/WHEEL
occli-0.3.5.dist-info/entry_points.txt
occli-0.3.5.dist-info/top_level.txt
occli-0.3.5.dist-info/RECORD
