Metadata-Version: 2.1
Name: occli
Version: 0.3.5
Summary: Open Corporates CLI
Home-page: https://github.com/rly0nheart/occli
Author: Richard Mwewa
Author-email: richardmwewa@duck.com
License: GNU General Public License v3 (GPLv3)
Classifier: Development Status :: 5 - Production/Stable
Classifier: Intended Audience :: Information Technology
Classifier: License :: OSI Approved :: GNU General Public License v3 (GPLv3)
Classifier: Operating System :: OS Independent
Classifier: Natural Language :: English
Classifier: Programming Language :: Python :: 3
License-File: LICENSE
Requires-Dist: requests
